collective.volto.subfooter-2.0.0-py3.11-nspkg.pth
collective/volto/subfooter/__init__.py
collective/volto/subfooter/configure.zcml
collective/volto/subfooter/interfaces.py
collective/volto/subfooter/permissions.zcml
collective/volto/subfooter/setuphandlers.py
collective/volto/subfooter/testing.py
collective/volto/subfooter/browser/__init__.py
collective/volto/subfooter/browser/configure.zcml
collective/volto/subfooter/browser/controlpanel.py
collective/volto/subfooter/locales/README.rst
collective/volto/subfooter/locales/__init__.py
collective/volto/subfooter/locales/collective.volto.subfooter.pot
collective/volto/subfooter/locales/update.py
collective/volto/subfooter/locales/update.sh
collective/volto/subfooter/locales/es/LC_MESSAGES/collective.volto.subfooter.po
collective/volto/subfooter/locales/it/LC_MESSAGES/collective.volto.subfooter.po
collective/volto/subfooter/profiles/default/browserlayer.xml
collective/volto/subfooter/profiles/default/controlpanel.xml
collective/volto/subfooter/profiles/default/metadata.xml
collective/volto/subfooter/profiles/default/registry.xml
collective/volto/subfooter/profiles/default/rolemap.xml
collective/volto/subfooter/profiles/uninstall/browserlayer.xml
collective/volto/subfooter/profiles/uninstall/controlpanel.xml
collective/volto/subfooter/profiles/uninstall/registry.xml
collective/volto/subfooter/restapi/__init__.py
collective/volto/subfooter/restapi/configure.zcml
collective/volto/subfooter/restapi/deserializer/__init__.py
collective/volto/subfooter/restapi/deserializer/configure.zcml
collective/volto/subfooter/restapi/deserializer/subfooter.py
collective/volto/subfooter/restapi/serializer/__init__.py
collective/volto/subfooter/restapi/serializer/configure.zcml
collective/volto/subfooter/restapi/serializer/subfooter.py
collective/volto/subfooter/restapi/services/__init__.py
collective/volto/subfooter/restapi/services/configure.zcml
collective/volto/subfooter/restapi/services/controlpanel.py
collective_volto_subfooter-2.0.0.dist-info/LICENSE.GPL
collective_volto_subfooter-2.0.0.dist-info/LICENSE.rst
collective_volto_subfooter-2.0.0.dist-info/METADATA
collective_volto_subfooter-2.0.0.dist-info/WHEEL
collective_volto_subfooter-2.0.0.dist-info/entry_points.txt
collective_volto_subfooter-2.0.0.dist-info/namespace_packages.txt
collective_volto_subfooter-2.0.0.dist-info/top_level.txt
collective_volto_subfooter-2.0.0.dist-info/RECORD
